{"nodes": [{"id": "src_juteprocurement_issue_py", "label": "issue.py", "file_type": "code", "source_file": "src\\juteProcurement\\issue.py", "source_location": "L1"}, {"id": "issue_juteissuecreate", "label": "JuteIssueCreate", "file_type": "code", "source_file": "src\\juteProcurement\\issue.py", "source_location": "L36"}, {"id": "basemodel", "label": "BaseModel", "file_type": "code", "source_file": "", "source_location": ""}, {"id": "issue_juteissueupdate", "label": "JuteIssueUpdate", "file_type": "code", "source_file": "src\\juteProcurement\\issue.py", "source_location": "L49"}, {"id": "issue_juteissuebulkcreate", "label": "JuteIssueBulkCreate", "file_type": "code", "source_file": "src\\juteProcurement\\issue.py", "source_location": "L59"}, {"id": "issue_juteissuestatusupdate", "label": "JuteIssueStatusUpdate", "file_type": "code", "source_file": "src\\juteProcurement\\issue.py", "source_location": "L66"}, {"id": "issue_get_jute_issue_table", "label": "get_jute_issue_table()", "file_type": "code", "source_file": "src\\juteProcurement\\issue.py", "source_location": "L79"}, {"id": "issue_get_jute_issue_by_id", "label": "get_jute_issue_by_id()", "file_type": "code", "source_file": "src\\juteProcurement\\issue.py", "source_location": "L152"}, {"id": "issue_get_issue_create_setup", "label": "get_issue_create_setup()", "file_type": "code", "source_file": "src\\juteProcurement\\issue.py", "source_location": "L226"}, {"id": "issue_get_stock_outstanding", "label": "get_stock_outstanding()", "file_type": "code", "source_file": "src\\juteProcurement\\issue.py", "source_location": "L277"}, {"id": "issue_get_issues_by_date", "label": "get_issues_by_date()", "file_type": "code", "source_file": "src\\juteProcurement\\issue.py", "source_location": "L324"}, {"id": "issue_get_max_issue_date", "label": "get_max_issue_date()", "file_type": "code", "source_file": "src\\juteProcurement\\issue.py", "source_location": "L407"}, {"id": "issue_create_issue", "label": "create_issue()", "file_type": "code", "source_file": "src\\juteProcurement\\issue.py", "source_location": "L452"}, {"id": "issue_update_issue", "label": "update_issue()", "file_type": "code", "source_file": "src\\juteProcurement\\issue.py", "source_location": "L531"}, {"id": "issue_delete_issue", "label": "delete_issue()", "file_type": "code", "source_file": "src\\juteProcurement\\issue.py", "source_location": "L623"}, {"id": "issue_open_issues", "label": "open_issues()", "file_type": "code", "source_file": "src\\juteProcurement\\issue.py", "source_location": "L667"}, {"id": "issue_approve_issues", "label": "approve_issues()", "file_type": "code", "source_file": "src\\juteProcurement\\issue.py", "source_location": "L735"}, {"id": "issue_reject_issues", "label": "reject_issues()", "file_type": "code", "source_file": "src\\juteProcurement\\issue.py", "source_location": "L803"}, {"id": "issue_rationale_1", "label": "Jute Issue API endpoints. Provides endpoints for viewing and managing jute issu", "file_type": "rationale", "source_file": "src\\juteProcurement\\issue.py", "source_location": "L1"}, {"id": "issue_rationale_37", "label": "Model for creating a jute issue line item.", "file_type": "rationale", "source_file": "src\\juteProcurement\\issue.py", "source_location": "L37"}, {"id": "issue_rationale_50", "label": "Model for updating a jute issue line item.", "file_type": "rationale", "source_file": "src\\juteProcurement\\issue.py", "source_location": "L50"}, {"id": "issue_rationale_60", "label": "Model for creating multiple jute issue line items.", "file_type": "rationale", "source_file": "src\\juteProcurement\\issue.py", "source_location": "L60"}, {"id": "issue_rationale_67", "label": "Model for updating issue status (open, approve, reject).", "file_type": "rationale", "source_file": "src\\juteProcurement\\issue.py", "source_location": "L67"}, {"id": "issue_rationale_84", "label": "Get paginated list of jute issue records.          Query params:     - co_id:", "file_type": "rationale", "source_file": "src\\juteProcurement\\issue.py", "source_location": "L84"}, {"id": "issue_rationale_158", "label": "Get a single jute issue record by ID.          Path params:     - issue_id: T", "file_type": "rationale", "source_file": "src\\juteProcurement\\issue.py", "source_location": "L158"}, {"id": "issue_rationale_231", "label": "Get setup data for creating jute issue.     Returns: jute items (item_grp_id 2", "file_type": "rationale", "source_file": "src\\juteProcurement\\issue.py", "source_location": "L231"}, {"id": "issue_rationale_282", "label": "Get available stock from vw_jute_stock_outstanding view.     Filters by branch_", "file_type": "rationale", "source_file": "src\\juteProcurement\\issue.py", "source_location": "L282"}, {"id": "issue_rationale_329", "label": "Get all jute issue line items for a specific branch and date.     Used for the", "file_type": "rationale", "source_file": "src\\juteProcurement\\issue.py", "source_location": "L329"}, {"id": "issue_rationale_412", "label": "Get the maximum issue date for a branch.     Used to set default date for new i", "file_type": "rationale", "source_file": "src\\juteProcurement\\issue.py", "source_location": "L412"}, {"id": "issue_rationale_458", "label": "Create a new jute issue line item.     Issue starts as Draft (status_id = 21).", "file_type": "rationale", "source_file": "src\\juteProcurement\\issue.py", "source_location": "L458"}, {"id": "issue_rationale_538", "label": "Update an existing jute issue line item.     Only allowed if status is Draft (2", "file_type": "rationale", "source_file": "src\\juteProcurement\\issue.py", "source_location": "L538"}, {"id": "issue_rationale_629", "label": "Delete a jute issue line item.     Only allowed if status is Draft (21).", "file_type": "rationale", "source_file": "src\\juteProcurement\\issue.py", "source_location": "L629"}, {"id": "issue_rationale_673", "label": "Open jute issues. Changes status from Draft (21) to Open (1).          Can ope", "file_type": "rationale", "source_file": "src\\juteProcurement\\issue.py", "source_location": "L673"}, {"id": "issue_rationale_741", "label": "Approve jute issues. Changes status from Open (1) to Approved (3).          Ca", "file_type": "rationale", "source_file": "src\\juteProcurement\\issue.py", "source_location": "L741"}, {"id": "issue_rationale_809", "label": "Reject jute issues. Changes status from Open (1) to Rejected (4).          Can", "file_type": "rationale", "source_file": "src\\juteProcurement\\issue.py", "source_location": "L809"}], "edges": [{"source": "src_juteprocurement_issue_py", "target": "fastapi", "relation": "imports_from", "confidence": "EXTRACTED", "source_file": "src\\juteProcurement\\issue.py", "source_location": "L7", "weight": 1.0}, {"source": "src_juteprocurement_issue_py", "target": "typing", "relation": "imports_from", "confidence": "EXTRACTED", "source_file": "src\\juteProcurement\\issue.py", "source_location": "L8", "weight": 1.0}, {"source": "src_juteprocurement_issue_py", "target": "pydantic", "relation": "imports_from", "confidence": "EXTRACTED", "source_file": "src\\juteProcurement\\issue.py", "source_location": "L9", "weight": 1.0}, {"source": "src_juteprocurement_issue_py", "target": "datetime", "relation": "imports_from", "confidence": "EXTRACTED", "source_file": "src\\juteProcurement\\issue.py", "source_location": "L10", "weight": 1.0}, {"source": "src_juteprocurement_issue_py", "target": "src_common_utils", "relation": "imports_from", "confidence": "EXTRACTED", "source_file": "src\\juteProcurement\\issue.py", "source_location": "L11", "weight": 1.0}, {"source": "src_juteprocurement_issue_py", "target": "logging", "relation": "imports", "confidence": "EXTRACTED", "source_file": "src\\juteProcurement\\issue.py", "source_location": "L12", "weight": 1.0}, {"source": "src_juteprocurement_issue_py", "target": "sqlalchemy_orm", "relation": "imports_from", "confidence": "EXTRACTED", "source_file": "src\\juteProcurement\\issue.py", "source_location": "L13", "weight": 1.0}, {"source": "src_juteprocurement_issue_py", "target": "sqlalchemy", "relation": "imports_from", "confidence": "EXTRACTED", "source_file": "src\\juteProcurement\\issue.py", "source_location": "L14", "weight": 1.0}, {"source": "src_juteprocurement_issue_py", "target": "src_config_db", "relation": "imports_from", "confidence": "EXTRACTED", "source_file": "src\\juteProcurement\\issue.py", "source_location": "L15", "weight": 1.0}, {"source": "src_juteprocurement_issue_py", "target": "src_authorization_utils", "relation": "imports_from", "confidence": "EXTRACTED", "source_file": "src\\juteProcurement\\issue.py", "source_location": "L16", "weight": 1.0}, {"source": "src_juteprocurement_issue_py", "target": "src_juteprocurement_query", "relation": "imports_from", "confidence": "EXTRACTED", "source_file": "src\\juteProcurement\\issue.py", "source_location": "L17", "weight": 1.0}, {"source": "src_juteprocurement_issue_py", "target": "issue_juteissuecreate", "relation": "contains", "confidence": "EXTRACTED", "source_file": "src\\juteProcurement\\issue.py", "source_location": "L36", "weight": 1.0}, {"source": "issue_juteissuecreate", "target": "basemodel", "relation": "inherits", "confidence": "EXTRACTED", "source_file": "src\\juteProcurement\\issue.py", "source_location": "L36", "weight": 1.0}, {"source": "src_juteprocurement_issue_py", "target": "issue_juteissueupdate", "relation": "contains", "confidence": "EXTRACTED", "source_file": "src\\juteProcurement\\issue.py", "source_location": "L49", "weight": 1.0}, {"source": "issue_juteissueupdate", "target": "basemodel", "relation": "inherits", "confidence": "EXTRACTED", "source_file": "src\\juteProcurement\\issue.py", "source_location": "L49", "weight": 1.0}, {"source": "src_juteprocurement_issue_py", "target": "issue_juteissuebulkcreate", "relation": "contains", "confidence": "EXTRACTED", "source_file": "src\\juteProcurement\\issue.py", "source_location": "L59", "weight": 1.0}, {"source": "issue_juteissuebulkcreate", "target": "basemodel", "relation": "inherits", "confidence": "EXTRACTED", "source_file": "src\\juteProcurement\\issue.py", "source_location": "L59", "weight": 1.0}, {"source": "src_juteprocurement_issue_py", "target": "issue_juteissuestatusupdate", "relation": "contains", "confidence": "EXTRACTED", "source_file": "src\\juteProcurement\\issue.py", "source_location": "L66", "weight": 1.0}, {"source": "issue_juteissuestatusupdate", "target": "basemodel", "relation": "inherits", "confidence": "EXTRACTED", "source_file": "src\\juteProcurement\\issue.py", "source_location": "L66", "weight": 1.0}, {"source": "src_juteprocurement_issue_py", "target": "issue_get_jute_issue_table", "relation": "contains", "confidence": "EXTRACTED", "source_file": "src\\juteProcurement\\issue.py", "source_location": "L79", "weight": 1.0}, {"source": "src_juteprocurement_issue_py", "target": "issue_get_jute_issue_by_id", "relation": "contains", "confidence": "EXTRACTED", "source_file": "src\\juteProcurement\\issue.py", "source_location": "L152", "weight": 1.0}, {"source": "src_juteprocurement_issue_py", "target": "issue_get_issue_create_setup", "relation": "contains", "confidence": "EXTRACTED", "source_file": "src\\juteProcurement\\issue.py", "source_location": "L226", "weight": 1.0}, {"source": "src_juteprocurement_issue_py", "target": "issue_get_stock_outstanding", "relation": "contains", "confidence": "EXTRACTED", "source_file": "src\\juteProcurement\\issue.py", "source_location": "L277", "weight": 1.0}, {"source": "src_juteprocurement_issue_py", "target": "issue_get_issues_by_date", "relation": "contains", "confidence": "EXTRACTED", "source_file": "src\\juteProcurement\\issue.py", "source_location": "L324", "weight": 1.0}, {"source": "src_juteprocurement_issue_py", "target": "issue_get_max_issue_date", "relation": "contains", "confidence": "EXTRACTED", "source_file": "src\\juteProcurement\\issue.py", "source_location": "L407", "weight": 1.0}, {"source": "src_juteprocurement_issue_py", "target": "issue_create_issue", "relation": "contains", "confidence": "EXTRACTED", "source_file": "src\\juteProcurement\\issue.py", "source_location": "L452", "weight": 1.0}, {"source": "src_juteprocurement_issue_py", "target": "issue_update_issue", "relation": "contains", "confidence": "EXTRACTED", "source_file": "src\\juteProcurement\\issue.py", "source_location": "L531", "weight": 1.0}, {"source": "src_juteprocurement_issue_py", "target": "issue_delete_issue", "relation": "contains", "confidence": "EXTRACTED", "source_file": "src\\juteProcurement\\issue.py", "source_location": "L623", "weight": 1.0}, {"source": "src_juteprocurement_issue_py", "target": "issue_open_issues", "relation": "contains", "confidence": "EXTRACTED", "source_file": "src\\juteProcurement\\issue.py", "source_location": "L667", "weight": 1.0}, {"source": "src_juteprocurement_issue_py", "target": "issue_approve_issues", "relation": "contains", "confidence": "EXTRACTED", "source_file": "src\\juteProcurement\\issue.py", "source_location": "L735", "weight": 1.0}, {"source": "src_juteprocurement_issue_py", "target": "issue_reject_issues", "relation": "contains", "confidence": "EXTRACTED", "source_file": "src\\juteProcurement\\issue.py", "source_location": "L803", "weight": 1.0}, {"source": "issue_rationale_1", "target": "src_juteprocurement_issue_py", "relation": "rationale_for", "confidence": "EXTRACTED", "source_file": "src\\juteProcurement\\issue.py", "source_location": "L1", "weight": 1.0}, {"source": "issue_rationale_37", "target": "issue_juteissuecreate", "relation": "rationale_for", "confidence": "EXTRACTED", "source_file": "src\\juteProcurement\\issue.py", "source_location": "L37", "weight": 1.0}, {"source": "issue_rationale_50", "target": "issue_juteissueupdate", "relation": "rationale_for", "confidence": "EXTRACTED", "source_file": "src\\juteProcurement\\issue.py", "source_location": "L50", "weight": 1.0}, {"source": "issue_rationale_60", "target": "issue_juteissuebulkcreate", "relation": "rationale_for", "confidence": "EXTRACTED", "source_file": "src\\juteProcurement\\issue.py", "source_location": "L60", "weight": 1.0}, {"source": "issue_rationale_67", "target": "issue_juteissuestatusupdate", "relation": "rationale_for", "confidence": "EXTRACTED", "source_file": "src\\juteProcurement\\issue.py", "source_location": "L67", "weight": 1.0}, {"source": "issue_rationale_84", "target": "issue_get_jute_issue_table", "relation": "rationale_for", "confidence": "EXTRACTED", "source_file": "src\\juteProcurement\\issue.py", "source_location": "L84", "weight": 1.0}, {"source": "issue_rationale_158", "target": "issue_get_jute_issue_by_id", "relation": "rationale_for", "confidence": "EXTRACTED", "source_file": "src\\juteProcurement\\issue.py", "source_location": "L158", "weight": 1.0}, {"source": "issue_rationale_231", "target": "issue_get_issue_create_setup", "relation": "rationale_for", "confidence": "EXTRACTED", "source_file": "src\\juteProcurement\\issue.py", "source_location": "L231", "weight": 1.0}, {"source": "issue_rationale_282", "target": "issue_get_stock_outstanding", "relation": "rationale_for", "confidence": "EXTRACTED", "source_file": "src\\juteProcurement\\issue.py", "source_location": "L282", "weight": 1.0}, {"source": "issue_rationale_329", "target": "issue_get_issues_by_date", "relation": "rationale_for", "confidence": "EXTRACTED", "source_file": "src\\juteProcurement\\issue.py", "source_location": "L329", "weight": 1.0}, {"source": "issue_rationale_412", "target": "issue_get_max_issue_date", "relation": "rationale_for", "confidence": "EXTRACTED", "source_file": "src\\juteProcurement\\issue.py", "source_location": "L412", "weight": 1.0}, {"source": "issue_rationale_458", "target": "issue_create_issue", "relation": "rationale_for", "confidence": "EXTRACTED", "source_file": "src\\juteProcurement\\issue.py", "source_location": "L458", "weight": 1.0}, {"source": "issue_rationale_538", "target": "issue_update_issue", "relation": "rationale_for", "confidence": "EXTRACTED", "source_file": "src\\juteProcurement\\issue.py", "source_location": "L538", "weight": 1.0}, {"source": "issue_rationale_629", "target": "issue_delete_issue", "relation": "rationale_for", "confidence": "EXTRACTED", "source_file": "src\\juteProcurement\\issue.py", "source_location": "L629", "weight": 1.0}, {"source": "issue_rationale_673", "target": "issue_open_issues", "relation": "rationale_for", "confidence": "EXTRACTED", "source_file": "src\\juteProcurement\\issue.py", "source_location": "L673", "weight": 1.0}, {"source": "issue_rationale_741", "target": "issue_approve_issues", "relation": "rationale_for", "confidence": "EXTRACTED", "source_file": "src\\juteProcurement\\issue.py", "source_location": "L741", "weight": 1.0}, {"source": "issue_rationale_809", "target": "issue_reject_issues", "relation": "rationale_for", "confidence": "EXTRACTED", "source_file": "src\\juteProcurement\\issue.py", "source_location": "L809", "weight": 1.0}]}