{"nodes": [{"id": "src_juteprocurement_mr_py", "label": "mr.py", "file_type": "code", "source_file": "src\\juteProcurement\\mr.py", "source_location": "L1"}, {"id": "mr_mrlineitemupdate", "label": "MRLineItemUpdate", "file_type": "code", "source_file": "src\\juteProcurement\\mr.py", "source_location": "L43"}, {"id": "basemodel", "label": "BaseModel", "file_type": "code", "source_file": "", "source_location": ""}, {"id": "mr_mrupdaterequest", "label": "MRUpdateRequest", "file_type": "code", "source_file": "src\\juteProcurement\\mr.py", "source_location": "L64"}, {"id": "mr_get_jute_mr_table", "label": "get_jute_mr_table()", "file_type": "code", "source_file": "src\\juteProcurement\\mr.py", "source_location": "L77"}, {"id": "mr_get_agent_options", "label": "get_agent_options()", "file_type": "code", "source_file": "src\\juteProcurement\\mr.py", "source_location": "L161"}, {"id": "mr_get_warehouse_options", "label": "get_warehouse_options()", "file_type": "code", "source_file": "src\\juteProcurement\\mr.py", "source_location": "L196"}, {"id": "mr_get_party_branches", "label": "get_party_branches()", "file_type": "code", "source_file": "src\\juteProcurement\\mr.py", "source_location": "L231"}, {"id": "mr_get_jute_mr_by_id", "label": "get_jute_mr_by_id()", "file_type": "code", "source_file": "src\\juteProcurement\\mr.py", "source_location": "L283"}, {"id": "mr_update_jute_mr", "label": "update_jute_mr()", "file_type": "code", "source_file": "src\\juteProcurement\\mr.py", "source_location": "L338"}, {"id": "mr_mrstatuschangerequest", "label": "MRStatusChangeRequest", "file_type": "code", "source_file": "src\\juteProcurement\\mr.py", "source_location": "L495"}, {"id": "mr_change_mr_status", "label": "change_mr_status()", "file_type": "code", "source_file": "src\\juteProcurement\\mr.py", "source_location": "L506"}, {"id": "mr_mrapprovalrequest", "label": "MRApprovalRequest", "file_type": "code", "source_file": "src\\juteProcurement\\mr.py", "source_location": "L614"}, {"id": "mr_get_next_branch_mr_no", "label": "get_next_branch_mr_no()", "file_type": "code", "source_file": "src\\juteProcurement\\mr.py", "source_location": "L641"}, {"id": "mr_get_next_mr_no_for_fy", "label": "get_next_mr_no_for_fy()", "file_type": "code", "source_file": "src\\juteProcurement\\mr.py", "source_location": "L652"}, {"id": "mr_get_next_bill_pass_no_for_fy", "label": "get_next_bill_pass_no_for_fy()", "file_type": "code", "source_file": "src\\juteProcurement\\mr.py", "source_location": "L690"}, {"id": "mr_get_cumulative_mr_value_for_party_in_fy", "label": "get_cumulative_mr_value_for_party_in_fy()", "file_type": "code", "source_file": "src\\juteProcurement\\mr.py", "source_location": "L739"}, {"id": "mr_calculate_mr_amounts", "label": "calculate_mr_amounts()", "file_type": "code", "source_file": "src\\juteProcurement\\mr.py", "source_location": "L784"}, {"id": "mr_calculate_tds_amount", "label": "calculate_tds_amount()", "file_type": "code", "source_file": "src\\juteProcurement\\mr.py", "source_location": "L814"}, {"id": "mr_calculate_roundoff", "label": "calculate_roundoff()", "file_type": "code", "source_file": "src\\juteProcurement\\mr.py", "source_location": "L849"}, {"id": "mr_open_mr", "label": "open_mr()", "file_type": "code", "source_file": "src\\juteProcurement\\mr.py", "source_location": "L860"}, {"id": "mr_pending_mr", "label": "pending_mr()", "file_type": "code", "source_file": "src\\juteProcurement\\mr.py", "source_location": "L949"}, {"id": "mr_approve_mr", "label": "approve_mr()", "file_type": "code", "source_file": "src\\juteProcurement\\mr.py", "source_location": "L1023"}, {"id": "mr_reject_mr", "label": "reject_mr()", "file_type": "code", "source_file": "src\\juteProcurement\\mr.py", "source_location": "L1309"}, {"id": "mr_cancel_mr", "label": "cancel_mr()", "file_type": "code", "source_file": "src\\juteProcurement\\mr.py", "source_location": "L1411"}, {"id": "mr_rationale_1", "label": "Jute Material Receipt (MR) API endpoints. Provides endpoints for viewing and ma", "file_type": "rationale", "source_file": "src\\juteProcurement\\mr.py", "source_location": "L1"}, {"id": "mr_rationale_44", "label": "Model for updating a jute_mr_li record.", "file_type": "rationale", "source_file": "src\\juteProcurement\\mr.py", "source_location": "L44"}, {"id": "mr_rationale_65", "label": "Request model for updating MR header and line items.", "file_type": "rationale", "source_file": "src\\juteProcurement\\mr.py", "source_location": "L65"}, {"id": "mr_rationale_82", "label": "Get paginated list of jute MR records.          Query params:     - co_id: Co", "file_type": "rationale", "source_file": "src\\juteProcurement\\mr.py", "source_location": "L82"}, {"id": "mr_rationale_166", "label": "Get agent options from jute_agent_map table.     Returns agent branches that ha", "file_type": "rationale", "source_file": "src\\juteProcurement\\mr.py", "source_location": "L166"}, {"id": "mr_rationale_201", "label": "Get warehouse options for a specific branch.     Returns warehouses with hierar", "file_type": "rationale", "source_file": "src\\juteProcurement\\mr.py", "source_location": "L201"}, {"id": "mr_rationale_236", "label": "Get party branches for a specific party.     Returns party branches with addres", "file_type": "rationale", "source_file": "src\\juteProcurement\\mr.py", "source_location": "L236"}, {"id": "mr_rationale_288", "label": "Get a single jute MR with line items.          Query params:     - id: MR ID", "file_type": "rationale", "source_file": "src\\juteProcurement\\mr.py", "source_location": "L288"}, {"id": "mr_rationale_345", "label": "Update jute MR header and line items.     Recalculates accepted_weight for each", "file_type": "rationale", "source_file": "src\\juteProcurement\\mr.py", "source_location": "L345"}, {"id": "mr_rationale_496", "label": "Request model for changing MR status.", "file_type": "rationale", "source_file": "src\\juteProcurement\\mr.py", "source_location": "L496"}, {"id": "mr_rationale_513", "label": "Change the status of a jute MR.          Validates that party_branch_id is set", "file_type": "rationale", "source_file": "src\\juteProcurement\\mr.py", "source_location": "L513"}, {"id": "mr_rationale_615", "label": "Request model for MR approval actions.", "file_type": "rationale", "source_file": "src\\juteProcurement\\mr.py", "source_location": "L615"}, {"id": "mr_rationale_642", "label": "Get the next branch_mr_no for the given branch (simple increment, no FY).", "file_type": "rationale", "source_file": "src\\juteProcurement\\mr.py", "source_location": "L642"}, {"id": "mr_rationale_653", "label": "Get the next MR number for the given branch and financial year.          MR nu", "file_type": "rationale", "source_file": "src\\juteProcurement\\mr.py", "source_location": "L653"}, {"id": "mr_rationale_691", "label": "Get the next Bill Pass number for the given branch and financial year.", "file_type": "rationale", "source_file": "src\\juteProcurement\\mr.py", "source_location": "L691"}, {"id": "mr_rationale_740", "label": "Get the cumulative value of all approved MRs for a party in the given financial", "file_type": "rationale", "source_file": "src\\juteProcurement\\mr.py", "source_location": "L740"}, {"id": "mr_rationale_785", "label": "Calculate total_amount, claim_amount for an MR from its line items.          F", "file_type": "rationale", "source_file": "src\\juteProcurement\\mr.py", "source_location": "L785"}, {"id": "mr_rationale_815", "label": "Calculate TDS amount based on cumulative MR value and threshold.          TDS", "file_type": "rationale", "source_file": "src\\juteProcurement\\mr.py", "source_location": "L815"}, {"id": "mr_rationale_850", "label": "Calculate roundoff to nearest rupee.          Returns the roundoff adjustment", "file_type": "rationale", "source_file": "src\\juteProcurement\\mr.py", "source_location": "L850"}, {"id": "mr_rationale_866", "label": "Open MR - Changes status from Draft (21) to Open (1).     Validates that party_", "file_type": "rationale", "source_file": "src\\juteProcurement\\mr.py", "source_location": "L866"}, {"id": "mr_rationale_955", "label": "Set MR to Pending status (13).     This is a terminal state on this screen - ha", "file_type": "rationale", "source_file": "src\\juteProcurement\\mr.py", "source_location": "L955"}, {"id": "mr_rationale_1029", "label": "Approve MR - Changes status to Approved (3) or advances approval level.     Can", "file_type": "rationale", "source_file": "src\\juteProcurement\\mr.py", "source_location": "L1029"}, {"id": "mr_rationale_1315", "label": "Reject MR - Changes status to Rejected (4).     Can only be done from Open (1)", "file_type": "rationale", "source_file": "src\\juteProcurement\\mr.py", "source_location": "L1315"}, {"id": "mr_rationale_1417", "label": "Cancel MR - Changes status to Cancelled (6).     Can only be done from Open (1)", "file_type": "rationale", "source_file": "src\\juteProcurement\\mr.py", "source_location": "L1417"}], "edges": [{"source": "src_juteprocurement_mr_py", "target": "fastapi", "relation": "imports_from", "confidence": "EXTRACTED", "source_file": "src\\juteProcurement\\mr.py", "source_location": "L6", "weight": 1.0}, {"source": "src_juteprocurement_mr_py", "target": "pydantic", "relation": "imports_from", "confidence": "EXTRACTED", "source_file": "src\\juteProcurement\\mr.py", "source_location": "L7", "weight": 1.0}, {"source": "src_juteprocurement_mr_py", "target": "typing", "relation": "imports_from", "confidence": "EXTRACTED", "source_file": "src\\juteProcurement\\mr.py", "source_location": "L8", "weight": 1.0}, {"source": "src_juteprocurement_mr_py", "target": "datetime", "relation": "imports_from", "confidence": "EXTRACTED", "source_file": "src\\juteProcurement\\mr.py", "source_location": "L9", "weight": 1.0}, {"source": "src_juteprocurement_mr_py", "target": "src_common_utils", "relation": "imports_from", "confidence": "EXTRACTED", "source_file": "src\\juteProcurement\\mr.py", "source_location": "L10", "weight": 1.0}, {"source": "src_juteprocurement_mr_py", "target": "logging", "relation": "imports", "confidence": "EXTRACTED", "source_file": "src\\juteProcurement\\mr.py", "source_location": "L11", "weight": 1.0}, {"source": "src_juteprocurement_mr_py", "target": "sqlalchemy_orm", "relation": "imports_from", "confidence": "EXTRACTED", "source_file": "src\\juteProcurement\\mr.py", "source_location": "L12", "weight": 1.0}, {"source": "src_juteprocurement_mr_py", "target": "sqlalchemy", "relation": "imports_from", "confidence": "EXTRACTED", "source_file": "src\\juteProcurement\\mr.py", "source_location": "L13", "weight": 1.0}, {"source": "src_juteprocurement_mr_py", "target": "src_config_db", "relation": "imports_from", "confidence": "EXTRACTED", "source_file": "src\\juteProcurement\\mr.py", "source_location": "L14", "weight": 1.0}, {"source": "src_juteprocurement_mr_py", "target": "src_authorization_utils", "relation": "imports_from", "confidence": "EXTRACTED", "source_file": "src\\juteProcurement\\mr.py", "source_location": "L15", "weight": 1.0}, {"source": "src_juteprocurement_mr_py", "target": "src_juteprocurement_query", "relation": "imports_from", "confidence": "EXTRACTED", "source_file": "src\\juteProcurement\\mr.py", "source_location": "L16", "weight": 1.0}, {"source": "src_juteprocurement_mr_py", "target": "src_common_approval_utils", "relation": "imports_from", "confidence": "EXTRACTED", "source_file": "src\\juteProcurement\\mr.py", "source_location": "L27", "weight": 1.0}, {"source": "src_juteprocurement_mr_py", "target": "src_juteprocurement_formatters", "relation": "imports_from", "confidence": "EXTRACTED", "source_file": "src\\juteProcurement\\mr.py", "source_location": "L28", "weight": 1.0}, {"source": "src_juteprocurement_mr_py", "target": "mr_mrlineitemupdate", "relation": "contains", "confidence": "EXTRACTED", "source_file": "src\\juteProcurement\\mr.py", "source_location": "L43", "weight": 1.0}, {"source": "mr_mrlineitemupdate", "target": "basemodel", "relation": "inherits", "confidence": "EXTRACTED", "source_file": "src\\juteProcurement\\mr.py", "source_location": "L43", "weight": 1.0}, {"source": "src_juteprocurement_mr_py", "target": "mr_mrupdaterequest", "relation": "contains", "confidence": "EXTRACTED", "source_file": "src\\juteProcurement\\mr.py", "source_location": "L64", "weight": 1.0}, {"source": "mr_mrupdaterequest", "target": "basemodel", "relation": "inherits", "confidence": "EXTRACTED", "source_file": "src\\juteProcurement\\mr.py", "source_location": "L64", "weight": 1.0}, {"source": "src_juteprocurement_mr_py", "target": "mr_get_jute_mr_table", "relation": "contains", "confidence": "EXTRACTED", "source_file": "src\\juteProcurement\\mr.py", "source_location": "L77", "weight": 1.0}, {"source": "src_juteprocurement_mr_py", "target": "mr_get_agent_options", "relation": "contains", "confidence": "EXTRACTED", "source_file": "src\\juteProcurement\\mr.py", "source_location": "L161", "weight": 1.0}, {"source": "src_juteprocurement_mr_py", "target": "mr_get_warehouse_options", "relation": "contains", "confidence": "EXTRACTED", "source_file": "src\\juteProcurement\\mr.py", "source_location": "L196", "weight": 1.0}, {"source": "src_juteprocurement_mr_py", "target": "mr_get_party_branches", "relation": "contains", "confidence": "EXTRACTED", "source_file": "src\\juteProcurement\\mr.py", "source_location": "L231", "weight": 1.0}, {"source": "src_juteprocurement_mr_py", "target": "mr_get_jute_mr_by_id", "relation": "contains", "confidence": "EXTRACTED", "source_file": "src\\juteProcurement\\mr.py", "source_location": "L283", "weight": 1.0}, {"source": "src_juteprocurement_mr_py", "target": "mr_update_jute_mr", "relation": "contains", "confidence": "EXTRACTED", "source_file": "src\\juteProcurement\\mr.py", "source_location": "L338", "weight": 1.0}, {"source": "src_juteprocurement_mr_py", "target": "mr_mrstatuschangerequest", "relation": "contains", "confidence": "EXTRACTED", "source_file": "src\\juteProcurement\\mr.py", "source_location": "L495", "weight": 1.0}, {"source": "mr_mrstatuschangerequest", "target": "basemodel", "relation": "inherits", "confidence": "EXTRACTED", "source_file": "src\\juteProcurement\\mr.py", "source_location": "L495", "weight": 1.0}, {"source": "src_juteprocurement_mr_py", "target": "mr_change_mr_status", "relation": "contains", "confidence": "EXTRACTED", "source_file": "src\\juteProcurement\\mr.py", "source_location": "L506", "weight": 1.0}, {"source": "src_juteprocurement_mr_py", "target": "mr_mrapprovalrequest", "relation": "contains", "confidence": "EXTRACTED", "source_file": "src\\juteProcurement\\mr.py", "source_location": "L614", "weight": 1.0}, {"source": "mr_mrapprovalrequest", "target": "basemodel", "relation": "inherits", "confidence": "EXTRACTED", "source_file": "src\\juteProcurement\\mr.py", "source_location": "L614", "weight": 1.0}, {"source": "src_juteprocurement_mr_py", "target": "mr_get_next_branch_mr_no", "relation": "contains", "confidence": "EXTRACTED", "source_file": "src\\juteProcurement\\mr.py", "source_location": "L641", "weight": 1.0}, {"source": "src_juteprocurement_mr_py", "target": "mr_get_next_mr_no_for_fy", "relation": "contains", "confidence": "EXTRACTED", "source_file": "src\\juteProcurement\\mr.py", "source_location": "L652", "weight": 1.0}, {"source": "src_juteprocurement_mr_py", "target": "mr_get_next_bill_pass_no_for_fy", "relation": "contains", "confidence": "EXTRACTED", "source_file": "src\\juteProcurement\\mr.py", "source_location": "L690", "weight": 1.0}, {"source": "src_juteprocurement_mr_py", "target": "mr_get_cumulative_mr_value_for_party_in_fy", "relation": "contains", "confidence": "EXTRACTED", "source_file": "src\\juteProcurement\\mr.py", "source_location": "L739", "weight": 1.0}, {"source": "src_juteprocurement_mr_py", "target": "mr_calculate_mr_amounts", "relation": "contains", "confidence": "EXTRACTED", "source_file": "src\\juteProcurement\\mr.py", "source_location": "L784", "weight": 1.0}, {"source": "src_juteprocurement_mr_py", "target": "mr_calculate_tds_amount", "relation": "contains", "confidence": "EXTRACTED", "source_file": "src\\juteProcurement\\mr.py", "source_location": "L814", "weight": 1.0}, {"source": "src_juteprocurement_mr_py", "target": "mr_calculate_roundoff", "relation": "contains", "confidence": "EXTRACTED", "source_file": "src\\juteProcurement\\mr.py", "source_location": "L849", "weight": 1.0}, {"source": "src_juteprocurement_mr_py", "target": "mr_open_mr", "relation": "contains", "confidence": "EXTRACTED", "source_file": "src\\juteProcurement\\mr.py", "source_location": "L860", "weight": 1.0}, {"source": "src_juteprocurement_mr_py", "target": "mr_pending_mr", "relation": "contains", "confidence": "EXTRACTED", "source_file": "src\\juteProcurement\\mr.py", "source_location": "L949", "weight": 1.0}, {"source": "src_juteprocurement_mr_py", "target": "mr_approve_mr", "relation": "contains", "confidence": "EXTRACTED", "source_file": "src\\juteProcurement\\mr.py", "source_location": "L1023", "weight": 1.0}, {"source": "src_juteprocurement_mr_py", "target": "mr_reject_mr", "relation": "contains", "confidence": "EXTRACTED", "source_file": "src\\juteProcurement\\mr.py", "source_location": "L1309", "weight": 1.0}, {"source": "src_juteprocurement_mr_py", "target": "mr_cancel_mr", "relation": "contains", "confidence": "EXTRACTED", "source_file": "src\\juteProcurement\\mr.py", "source_location": "L1411", "weight": 1.0}, {"source": "mr_approve_mr", "target": "mr_get_next_mr_no_for_fy", "relation": "calls", "confidence": "EXTRACTED", "source_file": "src\\juteProcurement\\mr.py", "source_location": "L1137", "weight": 1.0}, {"source": "mr_approve_mr", "target": "mr_get_next_bill_pass_no_for_fy", "relation": "calls", "confidence": "EXTRACTED", "source_file": "src\\juteProcurement\\mr.py", "source_location": "L1189", "weight": 1.0}, {"source": "mr_approve_mr", "target": "mr_calculate_mr_amounts", "relation": "calls", "confidence": "EXTRACTED", "source_file": "src\\juteProcurement\\mr.py", "source_location": "L1194", "weight": 1.0}, {"source": "mr_approve_mr", "target": "mr_get_cumulative_mr_value_for_party_in_fy", "relation": "calls", "confidence": "EXTRACTED", "source_file": "src\\juteProcurement\\mr.py", "source_location": "L1205", "weight": 1.0}, {"source": "mr_approve_mr", "target": "mr_calculate_tds_amount", "relation": "calls", "confidence": "EXTRACTED", "source_file": "src\\juteProcurement\\mr.py", "source_location": "L1208", "weight": 1.0}, {"source": "mr_approve_mr", "target": "mr_calculate_roundoff", "relation": "calls", "confidence": "EXTRACTED", "source_file": "src\\juteProcurement\\mr.py", "source_location": "L1216", "weight": 1.0}, {"source": "mr_rationale_1", "target": "src_juteprocurement_mr_py", "relation": "rationale_for", "confidence": "EXTRACTED", "source_file": "src\\juteProcurement\\mr.py", "source_location": "L1", "weight": 1.0}, {"source": "mr_rationale_44", "target": "mr_mrlineitemupdate", "relation": "rationale_for", "confidence": "EXTRACTED", "source_file": "src\\juteProcurement\\mr.py", "source_location": "L44", "weight": 1.0}, {"source": "mr_rationale_65", "target": "mr_mrupdaterequest", "relation": "rationale_for", "confidence": "EXTRACTED", "source_file": "src\\juteProcurement\\mr.py", "source_location": "L65", "weight": 1.0}, {"source": "mr_rationale_82", "target": "mr_get_jute_mr_table", "relation": "rationale_for", "confidence": "EXTRACTED", "source_file": "src\\juteProcurement\\mr.py", "source_location": "L82", "weight": 1.0}, {"source": "mr_rationale_166", "target": "mr_get_agent_options", "relation": "rationale_for", "confidence": "EXTRACTED", "source_file": "src\\juteProcurement\\mr.py", "source_location": "L166", "weight": 1.0}, {"source": "mr_rationale_201", "target": "mr_get_warehouse_options", "relation": "rationale_for", "confidence": "EXTRACTED", "source_file": "src\\juteProcurement\\mr.py", "source_location": "L201", "weight": 1.0}, {"source": "mr_rationale_236", "target": "mr_get_party_branches", "relation": "rationale_for", "confidence": "EXTRACTED", "source_file": "src\\juteProcurement\\mr.py", "source_location": "L236", "weight": 1.0}, {"source": "mr_rationale_288", "target": "mr_get_jute_mr_by_id", "relation": "rationale_for", "confidence": "EXTRACTED", "source_file": "src\\juteProcurement\\mr.py", "source_location": "L288", "weight": 1.0}, {"source": "mr_rationale_345", "target": "mr_update_jute_mr", "relation": "rationale_for", "confidence": "EXTRACTED", "source_file": "src\\juteProcurement\\mr.py", "source_location": "L345", "weight": 1.0}, {"source": "mr_rationale_496", "target": "mr_mrstatuschangerequest", "relation": "rationale_for", "confidence": "EXTRACTED", "source_file": "src\\juteProcurement\\mr.py", "source_location": "L496", "weight": 1.0}, {"source": "mr_rationale_513", "target": "mr_change_mr_status", "relation": "rationale_for", "confidence": "EXTRACTED", "source_file": "src\\juteProcurement\\mr.py", "source_location": "L513", "weight": 1.0}, {"source": "mr_rationale_615", "target": "mr_mrapprovalrequest", "relation": "rationale_for", "confidence": "EXTRACTED", "source_file": "src\\juteProcurement\\mr.py", "source_location": "L615", "weight": 1.0}, {"source": "mr_rationale_642", "target": "mr_get_next_branch_mr_no", "relation": "rationale_for", "confidence": "EXTRACTED", "source_file": "src\\juteProcurement\\mr.py", "source_location": "L642", "weight": 1.0}, {"source": "mr_rationale_653", "target": "mr_get_next_mr_no_for_fy", "relation": "rationale_for", "confidence": "EXTRACTED", "source_file": "src\\juteProcurement\\mr.py", "source_location": "L653", "weight": 1.0}, {"source": "mr_rationale_691", "target": "mr_get_next_bill_pass_no_for_fy", "relation": "rationale_for", "confidence": "EXTRACTED", "source_file": "src\\juteProcurement\\mr.py", "source_location": "L691", "weight": 1.0}, {"source": "mr_rationale_740", "target": "mr_get_cumulative_mr_value_for_party_in_fy", "relation": "rationale_for", "confidence": "EXTRACTED", "source_file": "src\\juteProcurement\\mr.py", "source_location": "L740", "weight": 1.0}, {"source": "mr_rationale_785", "target": "mr_calculate_mr_amounts", "relation": "rationale_for", "confidence": "EXTRACTED", "source_file": "src\\juteProcurement\\mr.py", "source_location": "L785", "weight": 1.0}, {"source": "mr_rationale_815", "target": "mr_calculate_tds_amount", "relation": "rationale_for", "confidence": "EXTRACTED", "source_file": "src\\juteProcurement\\mr.py", "source_location": "L815", "weight": 1.0}, {"source": "mr_rationale_850", "target": "mr_calculate_roundoff", "relation": "rationale_for", "confidence": "EXTRACTED", "source_file": "src\\juteProcurement\\mr.py", "source_location": "L850", "weight": 1.0}, {"source": "mr_rationale_866", "target": "mr_open_mr", "relation": "rationale_for", "confidence": "EXTRACTED", "source_file": "src\\juteProcurement\\mr.py", "source_location": "L866", "weight": 1.0}, {"source": "mr_rationale_955", "target": "mr_pending_mr", "relation": "rationale_for", "confidence": "EXTRACTED", "source_file": "src\\juteProcurement\\mr.py", "source_location": "L955", "weight": 1.0}, {"source": "mr_rationale_1029", "target": "mr_approve_mr", "relation": "rationale_for", "confidence": "EXTRACTED", "source_file": "src\\juteProcurement\\mr.py", "source_location": "L1029", "weight": 1.0}, {"source": "mr_rationale_1315", "target": "mr_reject_mr", "relation": "rationale_for", "confidence": "EXTRACTED", "source_file": "src\\juteProcurement\\mr.py", "source_location": "L1315", "weight": 1.0}, {"source": "mr_rationale_1417", "target": "mr_cancel_mr", "relation": "rationale_for", "confidence": "EXTRACTED", "source_file": "src\\juteProcurement\\mr.py", "source_location": "L1417", "weight": 1.0}]}