{"nodes": [{"id": "src_juteprocurement_juteagentmap_py", "label": "juteAgentMap.py", "file_type": "code", "source_file": "src\\juteProcurement\\juteAgentMap.py", "source_location": "L1"}, {"id": "juteagentmap_juteagentmapcreate", "label": "JuteAgentMapCreate", "file_type": "code", "source_file": "src\\juteProcurement\\juteAgentMap.py", "source_location": "L30"}, {"id": "basemodel", "label": "BaseModel", "file_type": "code", "source_file": "", "source_location": ""}, {"id": "juteagentmap_get_agent_map_table_query", "label": "get_agent_map_table_query()", "file_type": "code", "source_file": "src\\juteProcurement\\juteAgentMap.py", "source_location": "L40"}, {"id": "juteagentmap_get_agent_map_count_query", "label": "get_agent_map_count_query()", "file_type": "code", "source_file": "src\\juteProcurement\\juteAgentMap.py", "source_location": "L78"}, {"id": "juteagentmap_get_all_branches_with_company_query", "label": "get_all_branches_with_company_query()", "file_type": "code", "source_file": "src\\juteProcurement\\juteAgentMap.py", "source_location": "L97"}, {"id": "juteagentmap_get_party_branches_with_party_query", "label": "get_party_branches_with_party_query()", "file_type": "code", "source_file": "src\\juteProcurement\\juteAgentMap.py", "source_location": "L117"}, {"id": "juteagentmap_check_duplicate_mapping_query", "label": "check_duplicate_mapping_query()", "file_type": "code", "source_file": "src\\juteProcurement\\juteAgentMap.py", "source_location": "L144"}, {"id": "juteagentmap_get_jute_agent_map_table", "label": "get_jute_agent_map_table()", "file_type": "code", "source_file": "src\\juteProcurement\\juteAgentMap.py", "source_location": "L162"}, {"id": "juteagentmap_jute_agent_map_create_setup", "label": "jute_agent_map_create_setup()", "file_type": "code", "source_file": "src\\juteProcurement\\juteAgentMap.py", "source_location": "L210"}, {"id": "juteagentmap_get_party_branches_for_agent", "label": "get_party_branches_for_agent()", "file_type": "code", "source_file": "src\\juteProcurement\\juteAgentMap.py", "source_location": "L241"}, {"id": "juteagentmap_jute_agent_map_create", "label": "jute_agent_map_create()", "file_type": "code", "source_file": "src\\juteProcurement\\juteAgentMap.py", "source_location": "L275"}, {"id": "juteagentmap_jute_agent_map_delete", "label": "jute_agent_map_delete()", "file_type": "code", "source_file": "src\\juteProcurement\\juteAgentMap.py", "source_location": "L335"}, {"id": "juteagentmap_get_jute_agent_map_by_id", "label": "get_jute_agent_map_by_id()", "file_type": "code", "source_file": "src\\juteProcurement\\juteAgentMap.py", "source_location": "L374"}, {"id": "juteagentmap_rationale_1", "label": "Jute Agent Mapping API endpoints.  This module provides endpoints for managing", "file_type": "rationale", "source_file": "src\\juteProcurement\\juteAgentMap.py", "source_location": "L1"}, {"id": "juteagentmap_rationale_31", "label": "Request model for creating a jute agent mapping.", "file_type": "rationale", "source_file": "src\\juteProcurement\\juteAgentMap.py", "source_location": "L31"}, {"id": "juteagentmap_rationale_41", "label": "Query to get jute agent map list with branch and party details.     Displays: a", "file_type": "rationale", "source_file": "src\\juteProcurement\\juteAgentMap.py", "source_location": "L41"}, {"id": "juteagentmap_rationale_79", "label": "Query to get total count of agent mappings for pagination.", "file_type": "rationale", "source_file": "src\\juteProcurement\\juteAgentMap.py", "source_location": "L79"}, {"id": "juteagentmap_rationale_98", "label": "Query to get all branches with their company names for agent dropdown.     Retu", "file_type": "rationale", "source_file": "src\\juteProcurement\\juteAgentMap.py", "source_location": "L98"}, {"id": "juteagentmap_rationale_118", "label": "Query to get all party branches with their party names for party dropdown.", "file_type": "rationale", "source_file": "src\\juteProcurement\\juteAgentMap.py", "source_location": "L118"}, {"id": "juteagentmap_rationale_145", "label": "Check if a mapping already exists for the given agent_branch_id and party_branch", "file_type": "rationale", "source_file": "src\\juteProcurement\\juteAgentMap.py", "source_location": "L145"}, {"id": "juteagentmap_rationale_171", "label": "Get paginated list of jute agent mappings.          Returns agent branch (with", "file_type": "rationale", "source_file": "src\\juteProcurement\\juteAgentMap.py", "source_location": "L171"}, {"id": "juteagentmap_rationale_216", "label": "Get setup data for creating a jute agent mapping.          Returns:     - bra", "file_type": "rationale", "source_file": "src\\juteProcurement\\juteAgentMap.py", "source_location": "L216"}, {"id": "juteagentmap_rationale_247", "label": "Get available party branches for mapping to an agent.          Party branches", "file_type": "rationale", "source_file": "src\\juteProcurement\\juteAgentMap.py", "source_location": "L247"}, {"id": "juteagentmap_rationale_282", "label": "Create a new jute agent to party branch mapping.          Validates:     - ag", "file_type": "rationale", "source_file": "src\\juteProcurement\\juteAgentMap.py", "source_location": "L282"}, {"id": "juteagentmap_rationale_342", "label": "Delete a jute agent mapping by ID.          Validates that the mapping belongs", "file_type": "rationale", "source_file": "src\\juteProcurement\\juteAgentMap.py", "source_location": "L342"}, {"id": "juteagentmap_rationale_381", "label": "Get a single jute agent mapping by ID with full details.", "file_type": "rationale", "source_file": "src\\juteProcurement\\juteAgentMap.py", "source_location": "L381"}], "edges": [{"source": "src_juteprocurement_juteagentmap_py", "target": "fastapi", "relation": "imports_from", "confidence": "EXTRACTED", "source_file": "src\\juteProcurement\\juteAgentMap.py", "source_location": "L12", "weight": 1.0}, {"source": "src_juteprocurement_juteagentmap_py", "target": "sqlalchemy_orm", "relation": "imports_from", "confidence": "EXTRACTED", "source_file": "src\\juteProcurement\\juteAgentMap.py", "source_location": "L13", "weight": 1.0}, {"source": "src_juteprocurement_juteagentmap_py", "target": "sqlalchemy_sql", "relation": "imports_from", "confidence": "EXTRACTED", "source_file": "src\\juteProcurement\\juteAgentMap.py", "source_location": "L14", "weight": 1.0}, {"source": "src_juteprocurement_juteagentmap_py", "target": "datetime", "relation": "imports_from", "confidence": "EXTRACTED", "source_file": "src\\juteProcurement\\juteAgentMap.py", "source_location": "L15", "weight": 1.0}, {"source": "src_juteprocurement_juteagentmap_py", "target": "pydantic", "relation": "imports_from", "confidence": "EXTRACTED", "source_file": "src\\juteProcurement\\juteAgentMap.py", "source_location": "L16", "weight": 1.0}, {"source": "src_juteprocurement_juteagentmap_py", "target": "typing", "relation": "imports_from", "confidence": "EXTRACTED", "source_file": "src\\juteProcurement\\juteAgentMap.py", "source_location": "L17", "weight": 1.0}, {"source": "src_juteprocurement_juteagentmap_py", "target": "src_config_db", "relation": "imports_from", "confidence": "EXTRACTED", "source_file": "src\\juteProcurement\\juteAgentMap.py", "source_location": "L19", "weight": 1.0}, {"source": "src_juteprocurement_juteagentmap_py", "target": "src_authorization_utils", "relation": "imports_from", "confidence": "EXTRACTED", "source_file": "src\\juteProcurement\\juteAgentMap.py", "source_location": "L20", "weight": 1.0}, {"source": "src_juteprocurement_juteagentmap_py", "target": "src_models_jute", "relation": "imports_from", "confidence": "EXTRACTED", "source_file": "src\\juteProcurement\\juteAgentMap.py", "source_location": "L21", "weight": 1.0}, {"source": "src_juteprocurement_juteagentmap_py", "target": "juteagentmap_juteagentmapcreate", "relation": "contains", "confidence": "EXTRACTED", "source_file": "src\\juteProcurement\\juteAgentMap.py", "source_location": "L30", "weight": 1.0}, {"source": "juteagentmap_juteagentmapcreate", "target": "basemodel", "relation": "inherits", "confidence": "EXTRACTED", "source_file": "src\\juteProcurement\\juteAgentMap.py", "source_location": "L30", "weight": 1.0}, {"source": "src_juteprocurement_juteagentmap_py", "target": "juteagentmap_get_agent_map_table_query", "relation": "contains", "confidence": "EXTRACTED", "source_file": "src\\juteProcurement\\juteAgentMap.py", "source_location": "L40", "weight": 1.0}, {"source": "src_juteprocurement_juteagentmap_py", "target": "juteagentmap_get_agent_map_count_query", "relation": "contains", "confidence": "EXTRACTED", "source_file": "src\\juteProcurement\\juteAgentMap.py", "source_location": "L78", "weight": 1.0}, {"source": "src_juteprocurement_juteagentmap_py", "target": "juteagentmap_get_all_branches_with_company_query", "relation": "contains", "confidence": "EXTRACTED", "source_file": "src\\juteProcurement\\juteAgentMap.py", "source_location": "L97", "weight": 1.0}, {"source": "src_juteprocurement_juteagentmap_py", "target": "juteagentmap_get_party_branches_with_party_query", "relation": "contains", "confidence": "EXTRACTED", "source_file": "src\\juteProcurement\\juteAgentMap.py", "source_location": "L117", "weight": 1.0}, {"source": "src_juteprocurement_juteagentmap_py", "target": "juteagentmap_check_duplicate_mapping_query", "relation": "contains", "confidence": "EXTRACTED", "source_file": "src\\juteProcurement\\juteAgentMap.py", "source_location": "L144", "weight": 1.0}, {"source": "src_juteprocurement_juteagentmap_py", "target": "juteagentmap_get_jute_agent_map_table", "relation": "contains", "confidence": "EXTRACTED", "source_file": "src\\juteProcurement\\juteAgentMap.py", "source_location": "L162", "weight": 1.0}, {"source": "src_juteprocurement_juteagentmap_py", "target": "juteagentmap_jute_agent_map_create_setup", "relation": "contains", "confidence": "EXTRACTED", "source_file": "src\\juteProcurement\\juteAgentMap.py", "source_location": "L210", "weight": 1.0}, {"source": "src_juteprocurement_juteagentmap_py", "target": "juteagentmap_get_party_branches_for_agent", "relation": "contains", "confidence": "EXTRACTED", "source_file": "src\\juteProcurement\\juteAgentMap.py", "source_location": "L241", "weight": 1.0}, {"source": "src_juteprocurement_juteagentmap_py", "target": "juteagentmap_jute_agent_map_create", "relation": "contains", "confidence": "EXTRACTED", "source_file": "src\\juteProcurement\\juteAgentMap.py", "source_location": "L275", "weight": 1.0}, {"source": "src_juteprocurement_juteagentmap_py", "target": "juteagentmap_jute_agent_map_delete", "relation": "contains", "confidence": "EXTRACTED", "source_file": "src\\juteProcurement\\juteAgentMap.py", "source_location": "L335", "weight": 1.0}, {"source": "src_juteprocurement_juteagentmap_py", "target": "juteagentmap_get_jute_agent_map_by_id", "relation": "contains", "confidence": "EXTRACTED", "source_file": "src\\juteProcurement\\juteAgentMap.py", "source_location": "L374", "weight": 1.0}, {"source": "juteagentmap_get_jute_agent_map_table", "target": "juteagentmap_get_agent_map_table_query", "relation": "calls", "confidence": "EXTRACTED", "source_file": "src\\juteProcurement\\juteAgentMap.py", "source_location": "L186", "weight": 1.0}, {"source": "juteagentmap_get_jute_agent_map_table", "target": "juteagentmap_get_agent_map_count_query", "relation": "calls", "confidence": "EXTRACTED", "source_file": "src\\juteProcurement\\juteAgentMap.py", "source_location": "L194", "weight": 1.0}, {"source": "juteagentmap_jute_agent_map_create_setup", "target": "juteagentmap_get_all_branches_with_company_query", "relation": "calls", "confidence": "EXTRACTED", "source_file": "src\\juteProcurement\\juteAgentMap.py", "source_location": "L228", "weight": 1.0}, {"source": "juteagentmap_get_party_branches_for_agent", "target": "juteagentmap_get_party_branches_with_party_query", "relation": "calls", "confidence": "EXTRACTED", "source_file": "src\\juteProcurement\\juteAgentMap.py", "source_location": "L259", "weight": 1.0}, {"source": "juteagentmap_jute_agent_map_create", "target": "juteagentmap_check_duplicate_mapping_query", "relation": "calls", "confidence": "EXTRACTED", "source_file": "src\\juteProcurement\\juteAgentMap.py", "source_location": "L296", "weight": 1.0}, {"source": "juteagentmap_rationale_1", "target": "src_juteprocurement_juteagentmap_py", "relation": "rationale_for", "confidence": "EXTRACTED", "source_file": "src\\juteProcurement\\juteAgentMap.py", "source_location": "L1", "weight": 1.0}, {"source": "juteagentmap_rationale_31", "target": "juteagentmap_juteagentmapcreate", "relation": "rationale_for", "confidence": "EXTRACTED", "source_file": "src\\juteProcurement\\juteAgentMap.py", "source_location": "L31", "weight": 1.0}, {"source": "juteagentmap_rationale_41", "target": "juteagentmap_get_agent_map_table_query", "relation": "rationale_for", "confidence": "EXTRACTED", "source_file": "src\\juteProcurement\\juteAgentMap.py", "source_location": "L41", "weight": 1.0}, {"source": "juteagentmap_rationale_79", "target": "juteagentmap_get_agent_map_count_query", "relation": "rationale_for", "confidence": "EXTRACTED", "source_file": "src\\juteProcurement\\juteAgentMap.py", "source_location": "L79", "weight": 1.0}, {"source": "juteagentmap_rationale_98", "target": "juteagentmap_get_all_branches_with_company_query", "relation": "rationale_for", "confidence": "EXTRACTED", "source_file": "src\\juteProcurement\\juteAgentMap.py", "source_location": "L98", "weight": 1.0}, {"source": "juteagentmap_rationale_118", "target": "juteagentmap_get_party_branches_with_party_query", "relation": "rationale_for", "confidence": "EXTRACTED", "source_file": "src\\juteProcurement\\juteAgentMap.py", "source_location": "L118", "weight": 1.0}, {"source": "juteagentmap_rationale_145", "target": "juteagentmap_check_duplicate_mapping_query", "relation": "rationale_for", "confidence": "EXTRACTED", "source_file": "src\\juteProcurement\\juteAgentMap.py", "source_location": "L145", "weight": 1.0}, {"source": "juteagentmap_rationale_171", "target": "juteagentmap_get_jute_agent_map_table", "relation": "rationale_for", "confidence": "EXTRACTED", "source_file": "src\\juteProcurement\\juteAgentMap.py", "source_location": "L171", "weight": 1.0}, {"source": "juteagentmap_rationale_216", "target": "juteagentmap_jute_agent_map_create_setup", "relation": "rationale_for", "confidence": "EXTRACTED", "source_file": "src\\juteProcurement\\juteAgentMap.py", "source_location": "L216", "weight": 1.0}, {"source": "juteagentmap_rationale_247", "target": "juteagentmap_get_party_branches_for_agent", "relation": "rationale_for", "confidence": "EXTRACTED", "source_file": "src\\juteProcurement\\juteAgentMap.py", "source_location": "L247", "weight": 1.0}, {"source": "juteagentmap_rationale_282", "target": "juteagentmap_jute_agent_map_create", "relation": "rationale_for", "confidence": "EXTRACTED", "source_file": "src\\juteProcurement\\juteAgentMap.py", "source_location": "L282", "weight": 1.0}, {"source": "juteagentmap_rationale_342", "target": "juteagentmap_jute_agent_map_delete", "relation": "rationale_for", "confidence": "EXTRACTED", "source_file": "src\\juteProcurement\\juteAgentMap.py", "source_location": "L342", "weight": 1.0}, {"source": "juteagentmap_rationale_381", "target": "juteagentmap_get_jute_agent_map_by_id", "relation": "rationale_for", "confidence": "EXTRACTED", "source_file": "src\\juteProcurement\\juteAgentMap.py", "source_location": "L381", "weight": 1.0}]}