{"nodes": [{"id": "src_common_ctrldskadmin_users_py", "label": "users.py", "file_type": "code", "source_file": "src\\common\\ctrldskAdmin\\users.py", "source_location": "L1"}, {"id": "users_get_org_id_from_subdomain", "label": "get_org_id_from_subdomain()", "file_type": "code", "source_file": "src\\common\\ctrldskAdmin\\users.py", "source_location": "L22"}, {"id": "users_get_users_tenant_admin", "label": "get_users_tenant_admin()", "file_type": "code", "source_file": "src\\common\\ctrldskAdmin\\users.py", "source_location": "L63"}, {"id": "users_get_roles_tenant_admin_assign", "label": "get_roles_tenant_admin_assign()", "file_type": "code", "source_file": "src\\common\\ctrldskAdmin\\users.py", "source_location": "L160"}, {"id": "users_createusertenantadmin", "label": "CreateUserTenantAdmin", "file_type": "code", "source_file": "src\\common\\ctrldskAdmin\\users.py", "source_location": "L209"}, {"id": "basemodel", "label": "BaseModel", "file_type": "code", "source_file": "", "source_location": ""}, {"id": "users_create_user_tenant_admin", "label": "create_user_tenant_admin()", "file_type": "code", "source_file": "src\\common\\ctrldskAdmin\\users.py", "source_location": "L217"}, {"id": "users_editusertenantadmin", "label": "EditUserTenantAdmin", "file_type": "code", "source_file": "src\\common\\ctrldskAdmin\\users.py", "source_location": "L289"}, {"id": "users_edit_user_tenant_admin", "label": "edit_user_tenant_admin()", "file_type": "code", "source_file": "src\\common\\ctrldskAdmin\\users.py", "source_location": "L296"}, {"id": "users_get_orgs_dropdown_portal_user", "label": "get_orgs_dropdown_portal_user()", "file_type": "code", "source_file": "src\\common\\ctrldskAdmin\\users.py", "source_location": "L371"}, {"id": "users_createportaladminuser", "label": "CreatePortalAdminUser", "file_type": "code", "source_file": "src\\common\\ctrldskAdmin\\users.py", "source_location": "L399"}, {"id": "users_create_portal_admin_user", "label": "create_portal_admin_user()", "file_type": "code", "source_file": "src\\common\\ctrldskAdmin\\users.py", "source_location": "L407"}, {"id": "users_get_portal_admin_users", "label": "get_portal_admin_users()", "file_type": "code", "source_file": "src\\common\\ctrldskAdmin\\users.py", "source_location": "L553"}, {"id": "users_rationale_23", "label": "Get the organization ID for a given subdomain using raw SQL.      Args:", "file_type": "rationale", "source_file": "src\\common\\ctrldskAdmin\\users.py", "source_location": "L23"}, {"id": "users_rationale_70", "label": "Get list of users for tenant admin          Args:         request (Request):", "file_type": "rationale", "source_file": "src\\common\\ctrldskAdmin\\users.py", "source_location": "L70"}, {"id": "users_rationale_164", "label": "Get list of enabled roles for tenant admin assignment          Args:", "file_type": "rationale", "source_file": "src\\common\\ctrldskAdmin\\users.py", "source_location": "L164"}, {"id": "users_rationale_222", "label": "Create a new tenant admin user with role mapping          Args:         reque", "file_type": "rationale", "source_file": "src\\common\\ctrldskAdmin\\users.py", "source_location": "L222"}, {"id": "users_rationale_301", "label": "Update user role and active status for tenant admin          Args:         re", "file_type": "rationale", "source_file": "src\\common\\ctrldskAdmin\\users.py", "source_location": "L301"}, {"id": "users_rationale_374", "label": "Get list of active organisations for portal user creation dropdown.     Returns", "file_type": "rationale", "source_file": "src\\common\\ctrldskAdmin\\users.py", "source_location": "L374"}, {"id": "users_rationale_412", "label": "Create a full-access admin user for an organisation's portal (dashboardportal).", "file_type": "rationale", "source_file": "src\\common\\ctrldskAdmin\\users.py", "source_location": "L412"}, {"id": "users_rationale_560", "label": "Get list of portal admin users (con_user_type=1, con_org_id IS NOT NULL).", "file_type": "rationale", "source_file": "src\\common\\ctrldskAdmin\\users.py", "source_location": "L560"}], "edges": [{"source": "src_common_ctrldskadmin_users_py", "target": "typing", "relation": "imports_from", "confidence": "EXTRACTED", "source_file": "src\\common\\ctrldskAdmin\\users.py", "source_location": "L1", "weight": 1.0}, {"source": "src_common_ctrldskadmin_users_py", "target": "sqlalchemy_orm", "relation": "imports_from", "confidence": "EXTRACTED", "source_file": "src\\common\\ctrldskAdmin\\users.py", "source_location": "L2", "weight": 1.0}, {"source": "src_common_ctrldskadmin_users_py", "target": "sqlalchemy", "relation": "imports_from", "confidence": "EXTRACTED", "source_file": "src\\common\\ctrldskAdmin\\users.py", "source_location": "L3", "weight": 1.0}, {"source": "src_common_ctrldskadmin_users_py", "target": "sqlalchemy_sql", "relation": "imports_from", "confidence": "EXTRACTED", "source_file": "src\\common\\ctrldskAdmin\\users.py", "source_location": "L4", "weight": 1.0}, {"source": "src_common_ctrldskadmin_users_py", "target": "fastapi", "relation": "imports_from", "confidence": "EXTRACTED", "source_file": "src\\common\\ctrldskAdmin\\users.py", "source_location": "L5", "weight": 1.0}, {"source": "src_common_ctrldskadmin_users_py", "target": "pydantic", "relation": "imports_from", "confidence": "EXTRACTED", "source_file": "src\\common\\ctrldskAdmin\\users.py", "source_location": "L6", "weight": 1.0}, {"source": "src_common_ctrldskadmin_users_py", "target": "datetime", "relation": "imports_from", "confidence": "EXTRACTED", "source_file": "src\\common\\ctrldskAdmin\\users.py", "source_location": "L7", "weight": 1.0}, {"source": "src_common_ctrldskadmin_users_py", "target": "src_common_utils", "relation": "imports_from", "confidence": "EXTRACTED", "source_file": "src\\common\\ctrldskAdmin\\users.py", "source_location": "L8", "weight": 1.0}, {"source": "src_common_ctrldskadmin_users_py", "target": "src_config_db", "relation": "imports_from", "confidence": "EXTRACTED", "source_file": "src\\common\\ctrldskAdmin\\users.py", "source_location": "L9", "weight": 1.0}, {"source": "src_common_ctrldskadmin_users_py", "target": "src_authorization_utils", "relation": "imports_from", "confidence": "EXTRACTED", "source_file": "src\\common\\ctrldskAdmin\\users.py", "source_location": "L10", "weight": 1.0}, {"source": "src_common_ctrldskadmin_users_py", "target": "src_common_query", "relation": "imports_from", "confidence": "EXTRACTED", "source_file": "src\\common\\ctrldskAdmin\\users.py", "source_location": "L11", "weight": 1.0}, {"source": "src_common_ctrldskadmin_users_py", "target": "src_common_ctrldskadmin_models_py", "relation": "imports_from", "confidence": "EXTRACTED", "source_file": "src\\common\\ctrldskAdmin\\users.py", "source_location": "L12", "weight": 1.0}, {"source": "src_common_ctrldskadmin_users_py", "target": "users_get_org_id_from_subdomain", "relation": "contains", "confidence": "EXTRACTED", "source_file": "src\\common\\ctrldskAdmin\\users.py", "source_location": "L22", "weight": 1.0}, {"source": "src_common_ctrldskadmin_users_py", "target": "users_get_users_tenant_admin", "relation": "contains", "confidence": "EXTRACTED", "source_file": "src\\common\\ctrldskAdmin\\users.py", "source_location": "L63", "weight": 1.0}, {"source": "src_common_ctrldskadmin_users_py", "target": "users_get_roles_tenant_admin_assign", "relation": "contains", "confidence": "EXTRACTED", "source_file": "src\\common\\ctrldskAdmin\\users.py", "source_location": "L160", "weight": 1.0}, {"source": "src_common_ctrldskadmin_users_py", "target": "users_createusertenantadmin", "relation": "contains", "confidence": "EXTRACTED", "source_file": "src\\common\\ctrldskAdmin\\users.py", "source_location": "L209", "weight": 1.0}, {"source": "users_createusertenantadmin", "target": "basemodel", "relation": "inherits", "confidence": "EXTRACTED", "source_file": "src\\common\\ctrldskAdmin\\users.py", "source_location": "L209", "weight": 1.0}, {"source": "src_common_ctrldskadmin_users_py", "target": "users_create_user_tenant_admin", "relation": "contains", "confidence": "EXTRACTED", "source_file": "src\\common\\ctrldskAdmin\\users.py", "source_location": "L217", "weight": 1.0}, {"source": "src_common_ctrldskadmin_users_py", "target": "users_editusertenantadmin", "relation": "contains", "confidence": "EXTRACTED", "source_file": "src\\common\\ctrldskAdmin\\users.py", "source_location": "L289", "weight": 1.0}, {"source": "users_editusertenantadmin", "target": "basemodel", "relation": "inherits", "confidence": "EXTRACTED", "source_file": "src\\common\\ctrldskAdmin\\users.py", "source_location": "L289", "weight": 1.0}, {"source": "src_common_ctrldskadmin_users_py", "target": "users_edit_user_tenant_admin", "relation": "contains", "confidence": "EXTRACTED", "source_file": "src\\common\\ctrldskAdmin\\users.py", "source_location": "L296", "weight": 1.0}, {"source": "src_common_ctrldskadmin_users_py", "target": "users_get_orgs_dropdown_portal_user", "relation": "contains", "confidence": "EXTRACTED", "source_file": "src\\common\\ctrldskAdmin\\users.py", "source_location": "L371", "weight": 1.0}, {"source": "src_common_ctrldskadmin_users_py", "target": "users_createportaladminuser", "relation": "contains", "confidence": "EXTRACTED", "source_file": "src\\common\\ctrldskAdmin\\users.py", "source_location": "L399", "weight": 1.0}, {"source": "users_createportaladminuser", "target": "basemodel", "relation": "inherits", "confidence": "EXTRACTED", "source_file": "src\\common\\ctrldskAdmin\\users.py", "source_location": "L399", "weight": 1.0}, {"source": "src_common_ctrldskadmin_users_py", "target": "users_create_portal_admin_user", "relation": "contains", "confidence": "EXTRACTED", "source_file": "src\\common\\ctrldskAdmin\\users.py", "source_location": "L407", "weight": 1.0}, {"source": "src_common_ctrldskadmin_users_py", "target": "users_get_portal_admin_users", "relation": "contains", "confidence": "EXTRACTED", "source_file": "src\\common\\ctrldskAdmin\\users.py", "source_location": "L553", "weight": 1.0}, {"source": "users_rationale_23", "target": "users_get_org_id_from_subdomain", "relation": "rationale_for", "confidence": "EXTRACTED", "source_file": "src\\common\\ctrldskAdmin\\users.py", "source_location": "L23", "weight": 1.0}, {"source": "users_rationale_70", "target": "users_get_users_tenant_admin", "relation": "rationale_for", "confidence": "EXTRACTED", "source_file": "src\\common\\ctrldskAdmin\\users.py", "source_location": "L70", "weight": 1.0}, {"source": "users_rationale_164", "target": "users_get_roles_tenant_admin_assign", "relation": "rationale_for", "confidence": "EXTRACTED", "source_file": "src\\common\\ctrldskAdmin\\users.py", "source_location": "L164", "weight": 1.0}, {"source": "users_rationale_222", "target": "users_create_user_tenant_admin", "relation": "rationale_for", "confidence": "EXTRACTED", "source_file": "src\\common\\ctrldskAdmin\\users.py", "source_location": "L222", "weight": 1.0}, {"source": "users_rationale_301", "target": "users_edit_user_tenant_admin", "relation": "rationale_for", "confidence": "EXTRACTED", "source_file": "src\\common\\ctrldskAdmin\\users.py", "source_location": "L301", "weight": 1.0}, {"source": "users_rationale_374", "target": "users_get_orgs_dropdown_portal_user", "relation": "rationale_for", "confidence": "EXTRACTED", "source_file": "src\\common\\ctrldskAdmin\\users.py", "source_location": "L374", "weight": 1.0}, {"source": "users_rationale_412", "target": "users_create_portal_admin_user", "relation": "rationale_for", "confidence": "EXTRACTED", "source_file": "src\\common\\ctrldskAdmin\\users.py", "source_location": "L412", "weight": 1.0}, {"source": "users_rationale_560", "target": "users_get_portal_admin_users", "relation": "rationale_for", "confidence": "EXTRACTED", "source_file": "src\\common\\ctrldskAdmin\\users.py", "source_location": "L560", "weight": 1.0}]}